tracardi_rabbitmq_publisher/__init__.py
tracardi_rabbitmq_publisher/plugin.py
tracardi_rabbitmq_publisher/model/configuration.py
tracardi_rabbitmq_publisher/model/rabbit_configuration.py
tracardi_rabbitmq_publisher/model/__pycache__/configuration.cpython-38.pyc
tracardi_rabbitmq_publisher/model/__pycache__/rabbit_configuration.cpython-38.pyc
tracardi_rabbitmq_publisher/service/queue_publisher.py
tracardi_rabbitmq_publisher/service/__pycache__/queue_publisher.cpython-38.pyc
tracardi_rabbitmq_publisher/test/manual/publish.py
tracardi_rabbitmq_publisher-0.6.0.dist-info/LICENSE.md
tracardi_rabbitmq_publisher-0.6.0.dist-info/METADATA
tracardi_rabbitmq_publisher-0.6.0.dist-info/WHEEL
tracardi_rabbitmq_publisher-0.6.0.dist-info/top_level.txt
tracardi_rabbitmq_publisher-0.6.0.dist-info/RECORD
