Metadata-Version: 2.1
Name: tracardi-rabbitmq-publisher
Version: 0.6.0
Summary: The purpose of this plugin is publish payload to rabbitmq.
Home-page: UNKNOWN
Author: Risto Kowaczewski
Author-email: risto.kowaczewski@gmail.com
License: UNKNOWN
Keywords: tracardi,plugin
Platform: UNKNOWN
Classifier: Programming Language :: Python :: 3
Classifier: License :: OSI Approved :: MIT License
Classifier: Operating System :: OS Independent
Requires-Python: >=3.8
License-File: LICENSE.md
Requires-Dist: tracardi-plugin-sdk (>=0.6.22)
Requires-Dist: tracardi (>=0.6.10)
Requires-Dist: kombu (~=5.1.0)
Requires-Dist: pydantic (~=1.8.2)
